Metadata-Version: 2.1
Name: moodbot
Version: 1.1.9
Summary: Mood adaptive chatbot
Home-page: https://github.com/wa1ker38552/moodbot
Author: walker
Requires-Python: >=3.7
License-File: LICENSE.rst
